dlflow/__init__.py
dlflow/main.py
dlflow/engine/__init__.py
dlflow/engine/engine.py
dlflow/engine/workflow.py
dlflow/features/__init__.py
dlflow/features/feature_base.py
dlflow/features/feature_parser.py
dlflow/features/parser_local.py
dlflow/features/parser_spark.py
dlflow/mgr/__init__.py
dlflow/mgr/cfgmgr.py
dlflow/mgr/errors.py
dlflow/mgr/regmgr.py
dlflow/models/__init__.py
dlflow/models/input_base.py
dlflow/models/model_base.py
dlflow/models/internal/DNNBinaryClassifier.py
dlflow/models/internal/DNNRegression.py
dlflow/models/internal/NNDenseInput.py
dlflow/models/internal/__init__.py
dlflow/resources/locale/en/LC_MESSAGES/msg.mo
dlflow/resources/locale/zh/LC_MESSAGES/msg.mo
dlflow/tasks/__init__.py
dlflow/tasks/task_base.py
dlflow/tasks/internal/__init__.py
dlflow/tasks/internal/build.py
dlflow/tasks/internal/encode.py
dlflow/tasks/internal/evaluate.py
dlflow/tasks/internal/merge.py
dlflow/tasks/internal/predict.py
dlflow/tasks/internal/root.py
dlflow/tasks/internal/train.py
dlflow/utils/__init__.py
dlflow/utils/check.py
dlflow/utils/datetools.py
dlflow/utils/ftools.py
dlflow/utils/locale.py
dlflow/utils/logger.py
dlflow/utils/sparkapp.py
dlflow/utils/template.py
dlflow/utils/utilclass.py
dlflow-1.0.1.dist-info/LICENSE
dlflow-1.0.1.dist-info/METADATA
dlflow-1.0.1.dist-info/WHEEL
dlflow-1.0.1.dist-info/entry_points.txt
dlflow-1.0.1.dist-info/top_level.txt
dlflow-1.0.1.dist-info/RECORD
