Metadata-Version: 2.1
Name: dlflow
Version: 1.0.1
Summary: UNKNOWN
Home-page: https://github.com/didi/dlflow_github_private
Author: Profile
Author-email: profile@didiglobal.com
Maintainer: Qiwei Dou
Maintainer-email: douqiwei@didiglobal.com
License: Apache Software License
Platform: MacOS
Platform: Unix
Classifier: Development Status :: 4 - Beta
Classifier: Intended Audience :: Developers
Classifier: License :: OSI Approved :: Apache Software License
Classifier: Natural Language :: English
Classifier: Operating System :: MacOS
Classifier: Operating System :: POSIX :: Linux
Classifier: Programming Language :: Python :: 3.6
Requires-Python: >=3.6
Requires-Dist: findspark (==1.3.0)
Requires-Dist: tensorflow (==2.0.0)
Requires-Dist: pyhocon (==0.3.51)
Requires-Dist: ruamel-yaml (==0.15.46)
